setup.py
nose_lock/__init__.py
nose_lock.egg-info/PKG-INFO
nose_lock.egg-info/SOURCES.txt
nose_lock.egg-info/dependency_links.txt
nose_lock.egg-info/entry_points.txt
nose_lock.egg-info/requires.txt
nose_lock.egg-info/top_level.txt