Metadata-Version: 1.0
Name: nose-lock
Version: 0.2.2
Summary: A plugin for python-nose which locks test execution and doesn't allow to run them in parallel from two terminals.
Home-page: UNKNOWN
Author: Alxander Artemenko
Author-email: svetlyak.40wt@gmail.com
License: UNKNOWN
Platform: UNKNOWN
